basilpy/__init__.py
basilpy/basilpy.py
basilpy-0.0.7.dist-info/LICENSE
basilpy-0.0.7.dist-info/METADATA
basilpy-0.0.7.dist-info/WHEEL
basilpy-0.0.7.dist-info/top_level.txt
basilpy-0.0.7.dist-info/RECORD
