Metadata-Version: 2.1
Name: basilpy
Version: 0.0.7
Summary: Python code to estimate the signal from an On/Off measurementwith the BASiL approach [ PhysRevD.103.123001 ]
Home-page: https://github.com/giacomodamico24/basilpy
Author: Giacomo D'Amico
Author-email: giacomo.damico@uib.no
License: gpl-3.0
Keywords: gamma-ray astronomy,on/off measurements,signal estimation,Bayes
Platform: UNKNOWN
Classifier: Development Status :: 4 - Beta
Classifier: Intended Audience :: Science/Research
Classifier: Topic :: Scientific/Engineering :: Astronomy
Classifier: License :: OSI Approved :: GNU General Public License v3 (GPLv3)
Classifier: Programming Language :: Python :: 3.6
Classifier: Programming Language :: Python :: 3.7
Classifier: Programming Language :: Python :: 3.8
License-File: LICENSE
Requires-Dist: nbformat (>=4)
Requires-Dist: requests (>=2)
Requires-Dist: scipy (>=1)
Requires-Dist: numpy (>1.19)
Requires-Dist: mpmath (>=1.2)
